{
  "cabinet-big": {
    "height": 81,
    "pixelRatio": 3,
    "width": 75,
    "x": 450,
    "y": 0
  },
  "cabinet-big-highlight": {
    "height": 81,
    "pixelRatio": 3,
    "width": 75,
    "x": 525,
    "y": 0
  },
  "cabinet-big-purple": {
    "height": 81,
    "pixelRatio": 3,
    "width": 75,
    "x": 0,
    "y": 300
  },
  "cabinet-small": {
    "height": 69,
    "pixelRatio": 3,
    "width": 45,
    "x": 720,
    "y": 381
  },
  "cabinet-small-highlight": {
    "height": 69,
    "pixelRatio": 3,
    "width": 45,
    "x": 765,
    "y": 381
  },
  "cabinet-small-purple": {
    "height": 69,
    "pixelRatio": 3,
    "width": 45,
    "x": 810,
    "y": 381
  },
  "central-office-small": {
    "height": 72,
    "pixelRatio": 3,
    "width": 135,
    "x": 75,
    "y": 300
  },
  "central-office-small-highlight": {
    "height": 72,
    "pixelRatio": 3,
    "width": 135,
    "x": 210,
    "y": 300
  },
  "circle-2": {
    "height": 72,
    "pixelRatio": 3,
    "width": 72,
    "x": 345,
    "y": 300
  },
  "circle-3": {
    "height": 72,
    "pixelRatio": 3,
    "width": 72,
    "x": 417,
    "y": 300
  },
  "circle-bolt": {
    "height": 72,
    "pixelRatio": 3,
    "width": 72,
    "x": 489,
    "y": 300
  },
  "circle-with-m-1": {
    "height": 72,
    "pixelRatio": 3,
    "width": 72,
    "x": 0,
    "y": 381
  },
  "conduit-closure": {
    "height": 36,
    "pixelRatio": 3,
    "width": 60,
    "x": 1080,
    "y": 381
  },
  "conduit-closure-highlight": {
    "height": 36,
    "pixelRatio": 3,
    "width": 60,
    "x": 1140,
    "y": 381
  },
  "conduit-closure-purple": {
    "height": 36,
    "pixelRatio": 3,
    "width": 60,
    "x": 576,
    "y": 453
  },
  "drain-1": {
    "height": 72,
    "pixelRatio": 3,
    "width": 72,
    "x": 72,
    "y": 381
  },
  "drain-2": {
    "height": 72,
    "pixelRatio": 3,
    "width": 72,
    "x": 144,
    "y": 381
  },
  "example": {
    "height": 300,
    "pixelRatio": 3,
    "width": 300,
    "x": 0,
    "y": 0
  },
  "hand-hole": {
    "height": 69,
    "pixelRatio": 3,
    "width": 75,
    "x": 855,
    "y": 381
  },
  "hand-hole-highlight": {
    "height": 69,
    "pixelRatio": 3,
    "width": 75,
    "x": 930,
    "y": 381
  },
  "hand-hole-purple": {
    "height": 69,
    "pixelRatio": 3,
    "width": 75,
    "x": 1005,
    "y": 381
  },
  "house-1": {
    "height": 72,
    "pixelRatio": 3,
    "width": 72,
    "x": 216,
    "y": 381
  },
  "house-1-gray": {
    "height": 72,
    "pixelRatio": 3,
    "width": 72,
    "x": 288,
    "y": 381
  },
  "house-1-gray-highlight": {
    "height": 72,
    "pixelRatio": 3,
    "width": 72,
    "x": 360,
    "y": 381
  },
  "house-1-highlight": {
    "height": 72,
    "pixelRatio": 3,
    "width": 72,
    "x": 432,
    "y": 381
  },
  "house-1-olive": {
    "height": 72,
    "pixelRatio": 3,
    "width": 72,
    "x": 504,
    "y": 381
  },
  "house-1-olive-highlight": {
    "height": 72,
    "pixelRatio": 3,
    "width": 72,
    "x": 0,
    "y": 453
  },
  "house-2": {
    "height": 72,
    "pixelRatio": 3,
    "width": 72,
    "x": 72,
    "y": 453
  },
  "house-3": {
    "height": 72,
    "pixelRatio": 3,
    "width": 72,
    "x": 144,
    "y": 453
  },
  "house-4": {
    "height": 72,
    "pixelRatio": 3,
    "width": 72,
    "x": 216,
    "y": 453
  },
  "planned-dashed-circle": {
    "height": 150,
    "pixelRatio": 3,
    "width": 150,
    "x": 300,
    "y": 0
  },
  "questionmark-black": {
    "height": 72,
    "pixelRatio": 3,
    "width": 72,
    "x": 288,
    "y": 453
  },
  "spiral-1": {
    "height": 72,
    "pixelRatio": 3,
    "width": 72,
    "x": 360,
    "y": 453
  },
  "spiral-1-highlight": {
    "height": 72,
    "pixelRatio": 3,
    "width": 72,
    "x": 432,
    "y": 453
  },
  "spiral-1-purple": {
    "height": 72,
    "pixelRatio": 3,
    "width": 72,
    "x": 504,
    "y": 453
  },
  "splice-closure": {
    "height": 72,
    "pixelRatio": 3,
    "width": 72,
    "x": 0,
    "y": 525
  },
  "splice-closure-highlight": {
    "height": 72,
    "pixelRatio": 3,
    "width": 72,
    "x": 72,
    "y": 525
  },
  "splice-closure-purple": {
    "height": 72,
    "pixelRatio": 3,
    "width": 72,
    "x": 144,
    "y": 525
  },
  "star-black": {
    "height": 72,
    "pixelRatio": 3,
    "width": 72,
    "x": 216,
    "y": 525
  },
  "stripes-brown-2": {
    "height": 72,
    "pixelRatio": 3,
    "width": 72,
    "x": 288,
    "y": 525
  },
  "stripes-brown-new-1": {
    "height": 72,
    "pixelRatio": 3,
    "width": 72,
    "x": 360,
    "y": 525
  },
  "stripes-brown-new-2": {
    "height": 72,
    "pixelRatio": 3,
    "width": 72,
    "x": 432,
    "y": 525
  },
  "stripes-green-new-1": {
    "height": 72,
    "pixelRatio": 3,
    "width": 72,
    "x": 504,
    "y": 525
  },
  "stripes-green-new-2": {
    "height": 72,
    "pixelRatio": 3,
    "width": 72,
    "x": 576,
    "y": 381
  },
  "stripes_brown": {
    "height": 3,
    "pixelRatio": 3,
    "width": 3,
    "x": 636,
    "y": 453
  },
  "stripes_green": {
    "height": 3,
    "pixelRatio": 3,
    "width": 3,
    "x": 639,
    "y": 453
  },
  "triangle-black": {
    "height": 72,
    "pixelRatio": 3,
    "width": 72,
    "x": 648,
    "y": 381
  }
}